ogli/__init__.py
ogli/bootstrap.py
ogli/main.py
ogli/controllers/__init__.py
ogli/controllers/base.py
ogli/core/__init__.py
ogli/core/exc.py
ogli/core/version.py
ogli/ext/__init__.py
ogli/plugins/__init__.py
ogli/templates/__init__.py
ogli/templates/command1.jinja2
ogli-0.0.1.dist-info/LICENSE.md
ogli-0.0.1.dist-info/METADATA
ogli-0.0.1.dist-info/WHEEL
ogli-0.0.1.dist-info/entry_points.txt
ogli-0.0.1.dist-info/top_level.txt
ogli-0.0.1.dist-info/RECORD
