Metadata-Version: 2.1
Name: ogli
Version: 0.0.1
Summary: ogli integrates well!
Home-page: http://spectrumtech.net
Author: Shane Berry
Author-email: srberry1@gmail.com
License: unlicensed
Platform: UNKNOWN
